<?xml version="1.0" encoding="UTF-8"?>
<krpano>

<!-- ************************ -->
<!--         Messages         -->
<!-- ************************ -->

  <data name="ru_project_title"><![CDATA[New Project]]></data>


  <data name="ru_panogroup17_title"><![CDATA[ЖК Салават]]></data>

  <data name="ru_pano133_title"><![CDATA[Прихожая]]></data>
  <data name="ru_spotpolygon136_tooltip"><![CDATA[Кухня]]></data>
  <data name="ru_spotpolygon142_tooltip"><![CDATA[Санузел]]></data>
  <data name="ru_spotpolygon143_tooltip"><![CDATA[Гостиная]]></data>
  <data name="ru_pano16_title"><![CDATA[Санузел]]></data>
  <data name="ru_spotpolygon78_tooltip"><![CDATA[Прихожая]]></data>
  <data name="ru_pano15_title"><![CDATA[Кухня]]></data>
  <data name="ru_spotpolygon79_tooltip"><![CDATA[Прихожая]]></data>
  <data name="ru_pano129_title"><![CDATA[Гостиная]]></data>
  <data name="ru_spotpolygon144_tooltip"><![CDATA[Прихожая]]></data>
  <data name="ru_spotpolygon145_tooltip"><![CDATA[Спальная зона]]></data>
  <data name="ru_pano13_title"><![CDATA[Спальная зона]]></data>
  <data name="ru_spotpolygon82_tooltip"><![CDATA[Гостиная]]></data>
  <data name="ru_spotpolygon83_tooltip"><![CDATA[Прихожая]]></data>


  <data name="ru_pano125_title"><![CDATA[1готово-o]]></data>


  <data name="ru_pano126_title"><![CDATA[3готово-o]]></data>




	<data name="ru_project_floor_title"><![CDATA[New Project]]></data>
	<data name="ru_spotmap35_tooltip"><![CDATA[%p]]></data>
	<data name="ru_spotmap36_tooltip"><![CDATA[%p]]></data>
	<data name="ru_spotmap37_tooltip"><![CDATA[Спальная зона]]></data>
	<data name="ru_spotmap38_tooltip"><![CDATA[Санузел]]></data>
	<data name="ru_spotmap39_tooltip"><![CDATA[Кухня]]></data>

	<data name="ru_panogroup17_floor_title"><![CDATA[ЖК Салават]]></data>
	<data name="ru_spotmap41_tooltip"><![CDATA[Прихожая]]></data>
	<data name="ru_spotmap42_tooltip"><![CDATA[Санузел]]></data>
	<data name="ru_spotmap43_tooltip"><![CDATA[Кухня]]></data>
	<data name="ru_spotmap44_tooltip"><![CDATA[Гостиная]]></data>
	<data name="ru_spotmap45_tooltip"><![CDATA[Спальная зона]]></data>

  <data name="ru_contextmenuopenFsLabel"><![CDATA[Enter Fullscreen]]></data>
  <data name="ru_contextmenucloseFsLabel"><![CDATA[Exit Fullscreen]]></data>
  <data name="ru_contextmenunormallabel"><![CDATA[Normal View]]></data>
  <data name="ru_contextmenuarchitecturallabel"><![CDATA[Architectural View]]></data>
  <data name="ru_contextmenulittleplanetlabel"><![CDATA[Little Planet View]]></data>


  <data name="ru_vr_setup_hmd0"><![CDATA[SELECT YOUR HMD]]></data>
  <data name="ru_vr_setup_advanced"><![CDATA[ADVANCED SETTINGS]]></data>
  <data name="ru_vr_setup_title"><![CDATA[WEB VR SETTINGS]]></data>
  <data name="ru_vr_setup_dvn1"><![CDATA[Device:]]></data>
  <data name="ru_vr_setup_siz1"><![CDATA[Screen size:]]></data>
  <data name="ru_vr_setup_ipd1"><![CDATA[IPD:]]></data>
  <data name="ru_vr_setup_hmd1"><![CDATA[HMD:]]></data>
  <data name="ru_vr_setup_hmd3"><![CDATA[Customize]]></data>
  <data name="ru_vr_setup_cal"><![CDATA[Calibrate gyroscope]]></data>
  <data name="ru_vr_setup_sav"><![CDATA[SAVE]]></data>
  <data name="ru_vr_setup_rst"><![CDATA[RESET]]></data>
  <data name="ru_vr_setup_simple"><![CDATA[SIMPLE]]></data>
  <data name="ru_vr_setup_cls"><![CDATA[CLOSE]]></data>
  <data name="ru_vr_setup_m31"><![CDATA[HMD SETTINGS]]></data>
  <data name="ru_vr_setup_fov1"><![CDATA[FOV:]]></data>
  <data name="ru_vr_setup_dst1"><![CDATA[Distortion:]]></data>
  <data name="ru_vr_setup_d2tx"><![CDATA[Distortion 2:]]></data>
  <data name="ru_vr_setup_vig1"><![CDATA[Vignette:]]></data>
  <data name="ru_vr_setup_cac1"><![CDATA[Chromatic aberration:]]></data>
  <data name="ru_vr_setup_olp1"><![CDATA[Overlap:]]></data>
  <data name="ru_vr_setup_m35"><![CDATA[RETURN]]></data>
  <data name="ru_vr_setup_cb1"><![CDATA[GYROSCOPE]]></data>
  <data name="ru_vr_setup_cb2"><![CDATA[Place the device on a flat and[br]stable surface and tab CALIBRATE[br]to correct a gyroscope drifting.]]></data>
  <data name="ru_vr_setup_cb3"><![CDATA[CALIBRATE]]></data>
  <data name="ru_vr_setup_cb4"><![CDATA[RESET]]></data>
  <data name="ru_vr_setup_cb5"><![CDATA[RETURN]]></data>
  <data name="ru_vr_setup_cb6"><![CDATA[Calibrating...]]></data>
  <data name="ru_vr_setup_cb7"><![CDATA[Successful calibration]]></data>
  <data name="ru_vr_setup_cb8"><![CDATA[Calibration failed]]></data>
  <data name="ru_vr_setup_unavailable"><![CDATA[VR mode[br]is unavailable on your device]]></data>
















</krpano>